fastapi_ws_router/__about__.py
fastapi_ws_router/__init__.py
fastapi_ws_router/route.py
fastapi_ws_router/router.py
fastapi_ws_router-0.1.5.dist-info/METADATA
fastapi_ws_router-0.1.5.dist-info/WHEEL
fastapi_ws_router-0.1.5.dist-info/licenses/LICENSE.txt
fastapi_ws_router-0.1.5.dist-info/RECORD
