Metadata-Version: 2.3
Name: fastapi-ws-router
Version: 0.1.5
Summary: Include WebSocket messages in OpenAPI documentation generated by FastAPI
Project-URL: Documentation, https://github.com/mclate/fastapi-ws-router#readme
Project-URL: Issues, https://github.com/mclate/fastapi-ws-router/issues
Project-URL: Source, https://github.com/mclate/fastapi-ws-router
Author-email: Jack Zabolotnyi <git@mclate.com>
License-Expression: MIT
License-File: LICENSE.txt
Keywords: documentation,fastapi,openapi,swagger,websockets,ws
Classifier: Development Status :: 4 - Beta
Classifier: Programming Language :: Python
Classifier: Programming Language :: Python :: 3.9
Classifier: Programming Language :: Python :: 3.10
Classifier: Programming Language :: Python :: 3.11
Classifier: Programming Language :: Python :: 3.12
Classifier: Programming Language :: Python :: Implementation :: CPython
Classifier: Programming Language :: Python :: Implementation :: PyPy
Requires-Python: >=3.9
Requires-Dist: fastapi~=0.110.0
